{
    "swagger": "2.0",
    "info": {
        "title": "Online Voting System Swagger UI",
        "contact": {}
    },
    "basePath": "/",
    "paths": {
        "/admin/menu/create": {
            "post": {
                "security": [
                    {
                        "BearerAuth": []
                    }
                ],
                "description": "This api create menu",
                "consumes": [
                    "application/json"
                ],
                "produces": [
                    "application/json"
                ],
                "tags": [
                    "MENU"
                ],
                "summary": "Create Menu",
                "parameters": [
                    {
                        "description": "Menu",
                        "name": "data",
                        "in": "body",
                        "required": true,
                        "schema": {
                            "$ref": "#/definitions/genproto.Menu"
                        }
                    }
                ],
                "responses": {
                    "201": {
                        "description": "menu created successfully",
                        "schema": {
                            "type": "string"
                        }
                    },
                    "400": {
                        "description": "Bad Request",
                        "schema": {
                            "type": "string"
                        }
                    }
                }
            }
        },
        "/admin/menu/update": {
            "put": {
                "security": [
                    {
                        "BearerAuth": []
                    }
                ],
                "description": "This api UPDATES menu",
                "consumes": [
                    "application/json"
                ],
                "produces": [
                    "application/json"
                ],
                "tags": [
                    "MENU"
                ],
                "summary": "UPDATES MENU",
                "parameters": [
                    {
                        "description": "MENU",
                        "name": "reservation",
                        "in": "body",
                        "required": true,
                        "schema": {
                            "$ref": "#/definitions/genproto.Menu"
                        }
                    }
                ],
                "responses": {
                    "200": {
                        "description": "menu updated successfully",
                        "schema": {
                            "type": "string"
                        }
                    },
                    "400": {
                        "description": "Bad Request",
                        "schema": {
                            "type": "string"
                        }
                    },
                    "404": {
                        "description": "Not Found",
                        "schema": {
                            "type": "string"
                        }
                    }
                }
            }
        },
        "/admin/menu/{id}": {
            "delete": {
                "security": [
                    {
                        "BearerAuth": []
                    }
                ],
                "description": "This api DELETES menu by id",
                "consumes": [
                    "application/json"
                ],
                "produces": [
                    "application/json"
                ],
                "tags": [
                    "MENU"
                ],
                "summary": "DELETES Menu",
                "parameters": [
                    {
                        "type": "string",
                        "description": "MENU ID",
                        "name": "id",
                        "in": "path",
                        "required": true
                    }
                ],
                "responses": {
                    "200": {
                        "description": "menu deleted successfully",
                        "schema": {
                            "type": "string"
                        }
                    },
                    "400": {
                        "description": "Bad Request",
                        "schema": {
                            "type": "string"
                        }
                    },
                    "404": {
                        "description": "Not Found",
                        "schema": {
                            "type": "string"
                        }
                    }
                }
            }
        },
        "/admin/reservation/{id}": {
            "put": {
                "security": [
                    {
                        "BearerAuth": []
                    }
                ],
                "description": "This api UPDATES reservation by id",
                "consumes": [
                    "application/json"
                ],
                "produces": [
                    "application/json"
                ],
                "tags": [
                    "RESERVATION"
                ],
                "summary": "UPDATES RESERVATION",
                "parameters": [
                    {
                        "type": "string",
                        "description": "Reservation ID",
                        "name": "id",
                        "in": "path",
                        "required": true
                    },
                    {
                        "description": "RESERVATION",
                        "name": "reservation",
                        "in": "body",
                        "required": true,
                        "schema": {
                            "$ref": "#/definitions/genproto.Reservation"
                        }
                    }
                ],
                "responses": {
                    "200": {
                        "description": "reservation updated successfully",
                        "schema": {
                            "type": "string"
                        }
                    },
                    "400": {
                        "description": "Bad Request",
                        "schema": {
                            "type": "string"
                        }
                    },
                    "404": {
                        "description": "Not Found",
                        "schema": {
                            "type": "string"
                        }
                    }
                }
            },
            "delete": {
                "security": [
                    {
                        "BearerAuth": []
                    }
                ],
                "description": "This api DELETES reservation by id",
                "consumes": [
                    "application/json"
                ],
                "produces": [
                    "application/json"
                ],
                "tags": [
                    "RESERVATION"
                ],
                "summary": "DELETES RESERVATION",
                "parameters": [
                    {
                        "type": "string",
                        "description": "RESERVATION ID",
                        "name": "id",
                        "in": "path",
                        "required": true
                    }
                ],
                "responses": {
                    "200": {
                        "description": "reservation deleted successfully",
                        "schema": {
                            "type": "string"
                        }
                    },
                    "400": {
                        "description": "Bad Request",
                        "schema": {
                            "type": "string"
                        }
                    },
                    "404": {
                        "description": "Not Found",
                        "schema": {
                            "type": "string"
                        }
                    }
                }
            }
        },
        "/admin/restaurant/create": {
            "post": {
                "security": [
                    {
                        "BearerAuth": []
                    }
                ],
                "description": "This api create restaurant",
                "consumes": [
                    "application/json"
                ],
                "produces": [
                    "application/json"
                ],
                "tags": [
                    "RESTAURANT"
                ],
                "summary": "Create Restaurant",
                "parameters": [
                    {
                        "description": "CreateRestaurantReq",
                        "name": "data",
                        "in": "body",
                        "required": true,
                        "schema": {
                            "$ref": "#/definitions/genproto.CreateRestaurantReq"
                        }
                    }
                ],
                "responses": {
                    "201": {
                        "description": "Created",
                        "schema": {
                            "$ref": "#/definitions/genproto.Void"
                        }
                    },
                    "400": {
                        "description": "Bad Request",
                        "schema": {
                            "type": "string"
                        }
                    }
                }
            }
        },
        "/admin/restaurant/{id}": {
            "put": {
                "security": [
                    {
                        "BearerAuth": []
                    }
                ],
                "description": "This api logs  restaurant in",
                "consumes": [
                    "application/json"
                ],
                "produces": [
                    "application/json"
                ],
                "tags": [
                    "RESTAURANT"
                ],
                "summary": "Update Restaurant",
                "parameters": [
                    {
                        "type": "string",
                        "description": "Restaurant ID",
                        "name": "id",
                        "in": "path",
                        "required": true
                    },
                    {
                        "description": "Restaurant ",
                        "name": "restaurant",
                        "in": "body",
                        "required": true,
                        "schema": {
                            "$ref": "#/definitions/genproto.Restaurant"
                        }
                    }
                ],
                "responses": {
                    "201": {
                        "description": "Created",
                        "schema": {
                            "$ref": "#/definitions/genproto.Void"
                        }
                    },
                    "400": {
                        "description": "Bad Request",
                        "schema": {
                            "type": "string"
                        }
                    }
                }
            },
            "delete": {
                "security": [
                    {
                        "BearerAuth": []
                    }
                ],
                "description": "This api logs  restaurant in",
                "consumes": [
                    "application/json"
                ],
                "produces": [
                    "application/json"
                ],
                "tags": [
                    "RESTAURANT"
                ],
                "summary": "Delete Restaurant",
                "parameters": [
                    {
                        "type": "string",
                        "description": "RESTAURANT ID",
                        "name": "id",
                        "in": "path",
                        "required": true
                    }
                ],
                "responses": {
                    "201": {
                        "description": "Created",
                        "schema": {
                            "$ref": "#/definitions/genproto.Void"
                        }
                    },
                    "400": {
                        "description": "Bad Request",
                        "schema": {
                            "type": "string"
                        }
                    }
                }
            }
        },
        "/menu/all": {
            "get": {
                "security": [
                    {
                        "BearerAuth": []
                    }
                ],
                "description": "This api GETS ALL menus by id",
                "consumes": [
                    "application/json"
                ],
                "produces": [
                    "application/json"
                ],
                "tags": [
                    "MENU"
                ],
                "summary": "GETS ALL MENUS",
                "parameters": [
                    {
                        "type": "string",
                        "description": "RESTAURANT ID",
                        "name": "rest_id",
                        "in": "query"
                    },
                    {
                        "type": "string",
                        "description": "PriceFrom",
                        "name": "price_from",
                        "in": "query"
                    },
                    {
                        "type": "string",
                        "description": "PriceTo",
                        "name": "price_to",
                        "in": "query"
                    }
                ],
                "responses": {
                    "200": {
                        "description": "OK",
                        "schema": {
                            "$ref": "#/definitions/genproto.Reservation"
                        }
                    },
                    "400": {
                        "description": "Bad Request",
                        "schema": {
                            "type": "string"
                        }
                    },
                    "404": {
                        "description": "Not Found",
                        "schema": {
                            "type": "string"
                        }
                    }
                }
            }
        },
        "/menu/{id}": {
            "get": {
                "security": [
                    {
                        "BearerAuth": []
                    }
                ],
                "description": "This api GETS menu by id",
                "consumes": [
                    "application/json"
                ],
                "produces": [
                    "application/json"
                ],
                "tags": [
                    "MENU"
                ],
                "summary": "GET MENU",
                "parameters": [
                    {
                        "type": "string",
                        "description": "MENU ID",
                        "name": "id",
                        "in": "path",
                        "required": true
                    }
                ],
                "responses": {
                    "200": {
                        "description": "OK",
                        "schema": {
                            "$ref": "#/definitions/genproto.Menu"
                        }
                    },
                    "400": {
                        "description": "Bad Request",
                        "schema": {
                            "type": "string"
                        }
                    },
                    "404": {
                        "description": "Not Found",
                        "schema": {
                            "type": "string"
                        }
                    }
                }
            }
        },
        "/order/all": {
            "get": {
                "security": [
                    {
                        "BearerAuth": []
                    }
                ],
                "description": "This api logs order in",
                "consumes": [
                    "application/json"
                ],
                "produces": [
                    "application/json"
                ],
                "tags": [
                    "ORDER"
                ],
                "summary": "Get all Orders",
                "responses": {
                    "201": {
                        "description": "Created",
                        "schema": {
                            "$ref": "#/definitions/genproto.Orders"
                        }
                    },
                    "400": {
                        "description": "Bad Request",
                        "schema": {
                            "type": "string"
                        }
                    }
                }
            }
        },
        "/order/create": {
            "post": {
                "security": [
                    {
                        "BearerAuth": []
                    }
                ],
                "description": "This api create order",
                "consumes": [
                    "application/json"
                ],
                "produces": [
                    "application/json"
                ],
                "tags": [
                    "ORDER"
                ],
                "summary": "Create Order",
                "parameters": [
                    {
                        "description": "Void",
                        "name": "data",
                        "in": "body",
                        "required": true,
                        "schema": {
                            "$ref": "#/definitions/genproto.Order"
                        }
                    }
                ],
                "responses": {
                    "201": {
                        "description": "Created",
                        "schema": {
                            "$ref": "#/definitions/genproto.Void"
                        }
                    },
                    "400": {
                        "description": "Bad Request",
                        "schema": {
                            "type": "string"
                        }
                    }
                }
            }
        },
        "/order/{id}": {
            "get": {
                "security": [
                    {
                        "BearerAuth": []
                    }
                ],
                "description": "This api GETS order by id",
                "consumes": [
                    "application/json"
                ],
                "produces": [
                    "application/json"
                ],
                "tags": [
                    "ORDER"
                ],
                "summary": "GET ORDER",
                "parameters": [
                    {
                        "type": "string",
                        "description": "ORDER ID",
                        "name": "id",
                        "in": "path",
                        "required": true
                    }
                ],
                "responses": {
                    "200": {
                        "description": "OK",
                        "schema": {
                            "$ref": "#/definitions/genproto.Order"
                        }
                    },
                    "400": {
                        "description": "Bad Request",
                        "schema": {
                            "type": "string"
                        }
                    },
                    "404": {
                        "description": "Not Found",
                        "schema": {
                            "type": "string"
                        }
                    }
                }
            },
            "put": {
                "security": [
                    {
                        "BearerAuth": []
                    }
                ],
                "description": "This api logs order in",
                "consumes": [
                    "application/json"
                ],
                "produces": [
                    "application/json"
                ],
                "tags": [
                    "ORDER"
                ],
                "summary": "Update Order",
                "parameters": [
                    {
                        "type": "string",
                        "description": "ById",
                        "name": "id",
                        "in": "path",
                        "required": true
                    },
                    {
                        "type": "string",
                        "description": "Menu Item ID",
                        "name": "menu_item_id",
                        "in": "query"
                    },
                    {
                        "type": "string",
                        "description": "Reservation ID",
                        "name": "reservation_id",
                        "in": "query"
                    },
                    {
                        "type": "string",
                        "description": "Quantity",
                        "name": "quantity",
                        "in": "query"
                    }
                ],
                "responses": {
                    "201": {
                        "description": "Created",
                        "schema": {
                            "$ref": "#/definitions/genproto.Void"
                        }
                    },
                    "400": {
                        "description": "Bad Request",
                        "schema": {
                            "type": "string"
                        }
                    }
                }
            },
            "delete": {
                "security": [
                    {
                        "BearerAuth": []
                    }
                ],
                "description": "This api logs order in",
                "consumes": [
                    "application/json"
                ],
                "produces": [
                    "application/json"
                ],
                "tags": [
                    "ORDER"
                ],
                "summary": "Delete Order",
                "parameters": [
                    {
                        "type": "string",
                        "description": "ORDER ID",
                        "name": "id",
                        "in": "path",
                        "required": true
                    }
                ],
                "responses": {
                    "201": {
                        "description": "Created",
                        "schema": {
                            "$ref": "#/definitions/genproto.Void"
                        }
                    },
                    "400": {
                        "description": "Bad Request",
                        "schema": {
                            "type": "string"
                        }
                    }
                }
            }
        },
        "/payment/all": {
            "get": {
                "security": [
                    {
                        "BearerAuth": []
                    }
                ],
                "description": "This api gets all payments",
                "consumes": [
                    "application/json"
                ],
                "produces": [
                    "application/json"
                ],
                "tags": [
                    "PAYMENT"
                ],
                "summary": "Gets all Payments",
                "parameters": [
                    {
                        "type": "string",
                        "description": "PaymentMethod",
                        "name": "payment_method",
                        "in": "query"
                    },
                    {
                        "type": "string",
                        "description": "AmountFrom",
                        "name": "amount_from",
                        "in": "query"
                    },
                    {
                        "type": "string",
                        "description": "AmountTo",
                        "name": "amount_to",
                        "in": "query"
                    },
                    {
                        "type": "string",
                        "description": "PaymentStatus",
                        "name": "payment_status",
                        "in": "query"
                    }
                ],
                "responses": {
                    "201": {
                        "description": "Created",
                        "schema": {
                            "$ref": "#/definitions/genproto.Payment"
                        }
                    },
                    "400": {
                        "description": "Bad Request",
                        "schema": {
                            "type": "string"
                        }
                    }
                }
            }
        },
        "/payment/create": {
            "post": {
                "security": [
                    {
                        "BearerAuth": []
                    }
                ],
                "description": "This api creates payment",
                "consumes": [
                    "application/json"
                ],
                "produces": [
                    "application/json"
                ],
                "tags": [
                    "PAYMENT"
                ],
                "summary": "Creates Payment",
                "parameters": [
                    {
                        "description": "PaymentCreate",
                        "name": "data",
                        "in": "body",
                        "required": true,
                        "schema": {
                            "$ref": "#/definitions/genproto.PaymentCreate"
                        }
                    }
                ],
                "responses": {
                    "201": {
                        "description": "Created",
                        "schema": {
                            "$ref": "#/definitions/genproto.Payment"
                        }
                    },
                    "400": {
                        "description": "Bad Request",
                        "schema": {
                            "type": "string"
                        }
                    }
                }
            }
        },
        "/payment/update": {
            "put": {
                "security": [
                    {
                        "BearerAuth": []
                    }
                ],
                "description": "This api updates payment",
                "consumes": [
                    "application/json"
                ],
                "produces": [
                    "application/json"
                ],
                "tags": [
                    "PAYMENT"
                ],
                "summary": "Updates Payment",
                "parameters": [
                    {
                        "description": "PaymentCreate",
                        "name": "data",
                        "in": "body",
                        "required": true,
                        "schema": {
                            "$ref": "#/definitions/genproto.PaymentCreate"
                        }
                    }
                ],
                "responses": {
                    "201": {
                        "description": "Created",
                        "schema": {
                            "$ref": "#/definitions/genproto.Payment"
                        }
                    },
                    "400": {
                        "description": "Bad Request",
                        "schema": {
                            "type": "string"
                        }
                    }
                }
            }
        },
        "/payment/{id}": {
            "get": {
                "security": [
                    {
                        "BearerAuth": []
                    }
                ],
                "description": "This api gets payment",
                "consumes": [
                    "application/json"
                ],
                "produces": [
                    "application/json"
                ],
                "tags": [
                    "PAYMENT"
                ],
                "summary": "Gets Payment",
                "parameters": [
                    {
                        "type": "string",
                        "description": "PaymentCreate",
                        "name": "id",
                        "in": "path",
                        "required": true
                    }
                ],
                "responses": {
                    "201": {
                        "description": "Created",
                        "schema": {
                            "$ref": "#/definitions/genproto.Payment"
                        }
                    },
                    "400": {
                        "description": "Bad Request",
                        "schema": {
                            "type": "string"
                        }
                    }
                }
            }
        },
        "/reservation/all": {
            "get": {
                "security": [
                    {
                        "BearerAuth": []
                    }
                ],
                "description": "This api GETS ALL reservation by id",
                "consumes": [
                    "application/json"
                ],
                "produces": [
                    "application/json"
                ],
                "tags": [
                    "RESERVATION"
                ],
                "summary": "GETS ALL RESERVATION",
                "parameters": [
                    {
                        "type": "string",
                        "description": "RESTAURANT ID",
                        "name": "rest_id",
                        "in": "query"
                    },
                    {
                        "type": "string",
                        "description": "ReservationFrom",
                        "name": "time_from",
                        "in": "query"
                    },
                    {
                        "type": "string",
                        "description": "ReservationTo",
                        "name": "time_to",
                        "in": "query"
                    }
                ],
                "responses": {
                    "200": {
                        "description": "OK",
                        "schema": {
                            "$ref": "#/definitions/genproto.Reservation"
                        }
                    },
                    "400": {
                        "description": "Bad Request",
                        "schema": {
                            "type": "string"
                        }
                    },
                    "404": {
                        "description": "Not Found",
                        "schema": {
                            "type": "string"
                        }
                    }
                }
            }
        },
        "/reservation/create": {
            "post": {
                "security": [
                    {
                        "BearerAuth": []
                    }
                ],
                "description": "This api create reservation",
                "consumes": [
                    "application/json"
                ],
                "produces": [
                    "application/json"
                ],
                "tags": [
                    "RESERVATION"
                ],
                "summary": "Create Reservation",
                "parameters": [
                    {
                        "description": "ReservationCreate",
                        "name": "data",
                        "in": "body",
                        "required": true,
                        "schema": {
                            "$ref": "#/definitions/genproto.ReservationCreate"
                        }
                    }
                ],
                "responses": {
                    "201": {
                        "description": "reservation created successfully",
                        "schema": {
                            "type": "string"
                        }
                    },
                    "400": {
                        "description": "Bad Request",
                        "schema": {
                            "type": "string"
                        }
                    }
                }
            }
        },
        "/reservation/total/{id}": {
            "get": {
                "security": [
                    {
                        "BearerAuth": []
                    }
                ],
                "description": "This api GETS TOTAL PAYCHECK FOR reservation by id",
                "consumes": [
                    "application/json"
                ],
                "produces": [
                    "application/json"
                ],
                "tags": [
                    "RESERVATION"
                ],
                "summary": "GET TOTAL SUM FOR  RESERVATION",
                "parameters": [
                    {
                        "type": "string",
                        "description": "RESERVATION ID",
                        "name": "id",
                        "in": "path",
                        "required": true
                    }
                ],
                "responses": {
                    "200": {
                        "description": "OK",
                        "schema": {
                            "$ref": "#/definitions/genproto.Total"
                        }
                    },
                    "400": {
                        "description": "Bad Request",
                        "schema": {
                            "type": "string"
                        }
                    },
                    "404": {
                        "description": "Not Found",
                        "schema": {
                            "type": "string"
                        }
                    }
                }
            }
        },
        "/reservation/{id}": {
            "get": {
                "security": [
                    {
                        "BearerAuth": []
                    }
                ],
                "description": "This api GETS reservation by id",
                "consumes": [
                    "application/json"
                ],
                "produces": [
                    "application/json"
                ],
                "tags": [
                    "RESERVATION"
                ],
                "summary": "GET RESERVATION",
                "parameters": [
                    {
                        "type": "string",
                        "description": "RESERVATION ID",
                        "name": "id",
                        "in": "path",
                        "required": true
                    }
                ],
                "responses": {
                    "200": {
                        "description": "OK",
                        "schema": {
                            "$ref": "#/definitions/genproto.Reservation"
                        }
                    },
                    "400": {
                        "description": "Bad Request",
                        "schema": {
                            "type": "string"
                        }
                    },
                    "404": {
                        "description": "Not Found",
                        "schema": {
                            "type": "string"
                        }
                    }
                }
            }
        },
        "/reservation/{id}/add-order": {
            "post": {
                "security": [
                    {
                        "BearerAuth": []
                    }
                ],
                "description": "This api DELETES reservation by id",
                "consumes": [
                    "application/json"
                ],
                "produces": [
                    "application/json"
                ],
                "tags": [
                    "RESERVATION"
                ],
                "summary": "ADDS ORDER TO RESERVATION",
                "parameters": [
                    {
                        "type": "string",
                        "description": "RESERVATION ID",
                        "name": "id",
                        "in": "path",
                        "required": true
                    },
                    {
                        "description": "order data",
                        "name": "data",
                        "in": "body",
                        "required": true,
                        "schema": {
                            "$ref": "#/definitions/genproto.ReservationOrder"
                        }
                    }
                ],
                "responses": {
                    "200": {
                        "description": "order created successfully",
                        "schema": {
                            "type": "string"
                        }
                    },
                    "400": {
                        "description": "Bad Request",
                        "schema": {
                            "type": "string"
                        }
                    },
                    "404": {
                        "description": "Not Found",
                        "schema": {
                            "type": "string"
                        }
                    }
                }
            }
        },
        "/reservation/{id}/check": {
            "post": {
                "security": [
                    {
                        "BearerAuth": []
                    }
                ],
                "description": "This api CHECKS IF THE IT IS AVAILABLE FOR RESERVATION",
                "consumes": [
                    "application/json"
                ],
                "produces": [
                    "application/json"
                ],
                "tags": [
                    "RESERVATION"
                ],
                "summary": "CHECKS IF THE IT IS AVAILABLE FOR RESERVATION",
                "parameters": [
                    {
                        "description": "RESERVATION Check",
                        "name": "DATA",
                        "in": "body",
                        "required": true,
                        "schema": {
                            "$ref": "#/definitions/genproto.ResrvationTime"
                        }
                    }
                ],
                "responses": {
                    "200": {
                        "description": "this reservation time is not reserved yet!",
                        "schema": {
                            "type": "string"
                        }
                    },
                    "400": {
                        "description": "Bad Request",
                        "schema": {
                            "type": "string"
                        }
                    },
                    "404": {
                        "description": "Not Found",
                        "schema": {
                            "type": "string"
                        }
                    }
                }
            }
        },
        "/reservation/{id}/payment": {
            "post": {
                "security": [
                    {
                        "BearerAuth": []
                    }
                ],
                "description": "This api PAYS for reservation",
                "consumes": [
                    "application/json"
                ],
                "produces": [
                    "application/json"
                ],
                "tags": [
                    "RESERVATION"
                ],
                "summary": "PAYS FOR RESERVATION",
                "parameters": [
                    {
                        "type": "string",
                        "description": "RESERVATION ID",
                        "name": "id",
                        "in": "path",
                        "required": true
                    },
                    {
                        "description": "PAYMENT data",
                        "name": "data",
                        "in": "body",
                        "required": true,
                        "schema": {
                            "$ref": "#/definitions/genproto.ReservationPayment"
                        }
                    }
                ],
                "responses": {
                    "200": {
                        "description": "OK",
                        "schema": {
                            "$ref": "#/definitions/genproto.Payment"
                        }
                    },
                    "400": {
                        "description": "Bad Request",
                        "schema": {
                            "type": "string"
                        }
                    },
                    "404": {
                        "description": "Not Found",
                        "schema": {
                            "type": "string"
                        }
                    }
                }
            }
        },
        "/restaurant/all": {
            "get": {
                "security": [
                    {
                        "BearerAuth": []
                    }
                ],
                "description": "This api logs restaurant in",
                "consumes": [
                    "application/json"
                ],
                "produces": [
                    "application/json"
                ],
                "tags": [
                    "RESTAURANT"
                ],
                "summary": "Get all Restaurants",
                "parameters": [
                    {
                        "type": "string",
                        "description": "RESTAURANT Address",
                        "name": "address",
                        "in": "query"
                    }
                ],
                "responses": {
                    "200": {
                        "description": "OK",
                        "schema": {
                            "$ref": "#/definitions/genproto.Restaurants"
                        }
                    },
                    "400": {
                        "description": "Bad Request",
                        "schema": {
                            "type": "string"
                        }
                    }
                }
            }
        },
        "/restaurant/{id}": {
            "get": {
                "security": [
                    {
                        "BearerAuth": []
                    },
                    {
                        "BearerAuth": []
                    }
                ],
                "description": "This api GETS restaurant by id",
                "consumes": [
                    "application/json"
                ],
                "produces": [
                    "application/json"
                ],
                "tags": [
                    "RESTAURANT"
                ],
                "summary": "GET RESTAURANT",
                "parameters": [
                    {
                        "type": "string",
                        "description": "RESTAURANT ID",
                        "name": "id",
                        "in": "path",
                        "required": true
                    }
                ],
                "responses": {
                    "200": {
                        "description": "OK",
                        "schema": {
                            "$ref": "#/definitions/genproto.Restaurant"
                        }
                    },
                    "400": {
                        "description": "Bad Request",
                        "schema": {
                            "type": "string"
                        }
                    },
                    "404": {
                        "description": "Not Found",
                        "schema": {
                            "type": "string"
                        }
                    }
                }
            }
        }
    },
    "definitions": {
        "genproto.CreateRestaurantReq": {
            "type": "object",
            "properties": {
                "Address": {
                    "type": "string"
                },
                "Description": {
                    "type": "string"
                },
                "Id": {
                    "type": "string"
                },
                "Name": {
                    "type": "string"
                },
                "PhoneNumber": {
                    "type": "string"
                }
            }
        },
        "genproto.Menu": {
            "type": "object",
            "properties": {
                "Description": {
                    "type": "string"
                },
                "Id": {
                    "type": "string"
                },
                "Name": {
                    "type": "string"
                },
                "Price": {
                    "type": "number"
                },
                "RestaurantId": {
                    "type": "string"
                }
            }
        },
        "genproto.Order": {
            "type": "object",
            "properties": {
                "Id": {
                    "type": "string"
                },
                "MenuItemId": {
                    "type": "string"
                },
                "Quantity": {
                    "type": "integer"
                },
                "ReservationId": {
                    "type": "string"
                }
            }
        },
        "genproto.Orders": {
            "type": "object",
            "properties": {
                "Orders": {
                    "type": "array",
                    "items": {
                        "$ref": "#/definitions/genproto.Order"
                    }
                }
            }
        },
        "genproto.Payment": {
            "type": "object",
            "properties": {
                "Amount": {
                    "type": "number"
                },
                "Id": {
                    "type": "string"
                },
                "PaymentMethod": {
                    "type": "string"
                },
                "PaymentStatus": {
                    "type": "string"
                },
                "ReservationId": {
                    "type": "string"
                }
            }
        },
        "genproto.PaymentCreate": {
            "type": "object",
            "properties": {
                "Amount": {
                    "type": "number"
                },
                "Id": {
                    "type": "string"
                },
                "PaymentMethod": {
                    "type": "string"
                },
                "ReservationId": {
                    "type": "string"
                }
            }
        },
        "genproto.Reservation": {
            "type": "object",
            "properties": {
                "ReservationTime": {
                    "type": "string"
                },
                "RestaurantId": {
                    "type": "string"
                },
                "Status": {
                    "type": "string"
                },
                "User_id": {
                    "type": "string"
                }
            }
        },
        "genproto.ReservationCreate": {
            "type": "object",
            "properties": {
                "Id": {
                    "type": "string"
                },
                "ReservationTime": {
                    "type": "string"
                },
                "RestaurantId": {
                    "type": "string"
                },
                "Status": {
                    "type": "string"
                },
                "User_id": {
                    "type": "string"
                }
            }
        },
        "genproto.ReservationOrder": {
            "type": "object",
            "properties": {
                "MenuItemId": {
                    "type": "string"
                },
                "Quantity": {
                    "type": "integer"
                }
            }
        },
        "genproto.ReservationPayment": {
            "type": "object",
            "properties": {
                "Amount": {
                    "type": "number"
                },
                "PaymentMethod": {
                    "type": "string"
                }
            }
        },
        "genproto.ResrvationTime": {
            "type": "object",
            "properties": {
                "ReservationTime": {
                    "type": "string"
                },
                "RestaurantId": {
                    "type": "string"
                }
            }
        },
        "genproto.Restaurant": {
            "type": "object",
            "properties": {
                "Address": {
                    "type": "string"
                },
                "Description": {
                    "type": "string"
                },
                "Name": {
                    "type": "string"
                },
                "PhoneNumber": {
                    "type": "string"
                }
            }
        },
        "genproto.Restaurants": {
            "type": "object",
            "properties": {
                "Restaurants": {
                    "type": "array",
                    "items": {
                        "$ref": "#/definitions/genproto.Restaurant"
                    }
                }
            }
        },
        "genproto.Total": {
            "type": "object",
            "properties": {
                "Total": {
                    "type": "number"
                }
            }
        },
        "genproto.Void": {
            "type": "object"
        }
    },
    "securityDefinitions": {
        "BearerAuth": {
            "type": "apiKey",
            "name": "Authorization",
            "in": "header"
        }
    }
}